easy_twitter_interactors/__init__.py
easy_twitter_interactors/twitter_interactors/__init__.py
easy_twitter_interactors/twitter_interactors/constants.py
easy_twitter_interactors/twitter_interactors/exceptions.py
easy_twitter_interactors/twitter_interactors/twitter_likes.py
easy_twitter_interactors/twitter_interactors/twitter_reads.py
easy_twitter_interactors/twitter_utils/__init__.py
easy_twitter_interactors/twitter_utils/twitter_utils.py
easy_twitter_interactors-1.0.1.dist-info/LICENSE
easy_twitter_interactors-1.0.1.dist-info/METADATA
easy_twitter_interactors-1.0.1.dist-info/WHEEL
easy_twitter_interactors-1.0.1.dist-info/top_level.txt
easy_twitter_interactors-1.0.1.dist-info/RECORD
