Metadata-Version: 2.1
Name: easy-twitter-interactors
Version: 1.0.1
Summary: 简易、好用的推特(Twitter)点赞，刷阅读量程序
Home-page: https://easy-twitter-interactors.xink.top/
Author: hanxinkong
Author-email: xinkonghan@gmail.com
License: MIT
Keywords: easy,twitter,interactors,reads
Requires-Python: >=3.6.8
License-File: LICENSE
Requires-Dist: easy-spider-tool (==1.0.7)
Requires-Dist: loguru (==0.7.0)
Requires-Dist: requests (==2.27.1)
Requires-Dist: urllib3 (==1.26.15)
